<?xml version = '1.0' encoding = 'UTF-8'?>
<TableProxyOraclev12c class="oracle.dbtools.crest.model.design.storage.oracle.v12c.TableProxyOraclev12c" name="ZONA_ACTIVIDADES" directorySegmentName="seg_0" id="4D6759FC-5DD6-3A4B-C57A-82E8BE430652">
<createdBy>Zaloon098</createdBy>
<createdTime>2023-01-07 09:03:25 UTC</createdTime>
<ownerDesignName>CarcelFinal</ownerDesignName>
<schemaObject>3E8F0D20-E821-FAAC-492E-E7E581CA4A8C</schemaObject>
<logging>YES</logging>
<partitionedRowMovement>DISABLE</partitionedRowMovement>
<segment>D991BD49-1E9E-C7A2-1E8C-469366376174</segment>
<tableSpace>27AA2570-5C08-77DD-CE1D-005852617FE9</tableSpace>
<temporaryChanged>false</temporaryChanged>
<accessDriverType>oracle_loader</accessDriverType>
<rejectLimit></rejectLimit>
<inMemory>NO</inMemory>
<columnProxies itemClass="oracle.dbtools.crest.model.design.storage.oracle.v12c.ColumnProxyOraclev12c">
<ColumnProxy name="TIPO" id="3B23F0F5-EFFC-2A5F-D532-D3E0824E785C">
<createdBy>Zaloon098</createdBy>
<createdTime>2023-01-07 09:03:25 UTC</createdTime>
<ownerDesignName>CarcelFinal</ownerDesignName>
</ColumnProxy>
<ColumnProxy name="AFORO_MAX" id="73D5B143-6801-D36A-38F3-844EDF9F5CD8">
<createdBy>Zaloon098</createdBy>
<createdTime>2023-01-07 09:03:25 UTC</createdTime>
<ownerDesignName>CarcelFinal</ownerDesignName>
</ColumnProxy>
<ColumnProxy name="COD_CARCEL" id="A8F389EF-A9FE-F6D7-8BDB-0086C03CB243">
<createdBy>Zaloon098</createdBy>
<createdTime>2023-01-07 09:03:25 UTC</createdTime>
<ownerDesignName>CarcelFinal</ownerDesignName>
</ColumnProxy>
<ColumnProxy name="ID_ZONA" id="EFE3E074-629B-5623-CDCF-1F1E0CD4EACF">
<createdBy>Zaloon098</createdBy>
<createdTime>2023-01-07 09:03:25 UTC</createdTime>
<ownerDesignName>CarcelFinal</ownerDesignName>
</ColumnProxy>
</columnProxies>
<indexProxies>
<IndexProxy class="oracle.dbtools.crest.model.design.storage.oracle.v10g.IndexProxyOraclev10g" name="ZONA_ACTIVIDADES_PK" id="B4BE4DAB-995E-BF93-EE53-053B2408354B">
<createdBy>Zaloon098</createdBy>
<createdTime>2023-01-07 09:03:26 UTC</createdTime>
<ownerDesignName>CarcelFinal</ownerDesignName>
<schemaObject>3E8F0D20-E821-FAAC-492E-E7E581CA4A8C</schemaObject>
<segment>8C9A1F3D-BF06-61B7-E360-28A5C60363DF</segment>
<tableSpace>27AA2570-5C08-77DD-CE1D-005852617FE9</tableSpace>
</IndexProxy>
</indexProxies>
<foreignKeys>
<ForeignKey class="oracle.dbtools.crest.model.design.storage.oracle.v10g.FKProxyOraclev10g" name="ZONA_ACTIVIDADES_CARCEL_FK" id="5B8C86F0-C532-4859-CA53-586BD17DEBF7">
<createdBy>Zaloon098</createdBy>
<createdTime>2023-01-07 09:03:31 UTC</createdTime>
<ownerDesignName>CarcelFinal</ownerDesignName>
</ForeignKey>
</foreignKeys>
<primaryKeys>
<PrimaryKey class="oracle.dbtools.crest.model.design.storage.oracle.v10g.PKProxyOraclev10g" name="ZONA_ACTIVIDADES_PK" id="D81AC074-B0FE-760E-2322-66A98E6E5DA7">
<createdBy>Zaloon098</createdBy>
<createdTime>2023-01-07 09:03:27 UTC</createdTime>
<ownerDesignName>CarcelFinal</ownerDesignName>
<segment>8C9A1F3D-BF06-61B7-E360-28A5C60363DF</segment>
<tableSpace>27AA2570-5C08-77DD-CE1D-005852617FE9</tableSpace>
<existingIndex>B4BE4DAB-995E-BF93-EE53-053B2408354B</existingIndex>
<indexSegment>8C9A1F3D-BF06-61B7-E360-28A5C60363DF</indexSegment>
<indexSort>SORTED</indexSort>
<usingIndex>BY INDEX NAME</usingIndex>
</PrimaryKey>
</primaryKeys>
</TableProxyOraclev12c>